[
  {
    "id": 1,
    "title": "Avocado Toast with Egg",
    "description": "Crispy toast topped with smashed avocado and soft-boiled egg.",
    "image_url": "https://www.jessicagavin.com/wp-content/uploads/2020/07/avocado-toast-20-1200x1800.jpg",
    "category": "with_light",
    "type_of_dish": "breakfast",
    "cooking_time": 15,
    "complexity": "easy",
    "view_count": 124,
    "instructions": [
      { "id": 1, "recipe_title": "Avocado Toast with Egg", "text": "1. Toast the bread." },
      { "id": 2, "recipe_title": "Avocado Toast with Egg", "text": "2. Mash avocado with salt and pepper. Spread on toast." },
      { "id": 3, "recipe_title": "Avocado Toast with Egg", "text": "3. Add sliced soft-boiled egg on top and serve." }
    ],
    "ingredients": [
      { "id": 1, "name": "Bread", "quantity": 2, "unit": "pcs" },
      { "id": 2, "name": "Avocado", "quantity": 1, "unit": "pcs" },
      { "id": 3, "name": "Eggs", "quantity": 2, "unit": "pcs" }
    ]
  },

  {
    "id": 2,
    "title": "No-Cook Tuna Sandwich",
    "description": "Quick tuna sandwich perfect for blackout situations.",
    "image_url": "https://cdn11.bigcommerce.com/s-cjh14ahqln/product_images/uploaded_images/tunacannellinibeansalad-1-web.jpg",
    "category": "no_light",
    "type_of_dish": "lunch",
    "cooking_time": 10,
    "complexity": "easy",
    "view_count": 98,
    "instructions": [
      { "id": 1, "recipe_title": "No-Cook Tuna Sandwich", "text": "1. Mix canned tuna with mayonnaise and salt." },
      { "id": 2, "recipe_title": "No-Cook Tuna Sandwich", "text": "2. Spread on bread slices." },
      { "id": 3, "recipe_title": "No-Cook Tuna Sandwich", "text": "3. Add lettuce and assemble the sandwich." }
    ],
    "ingredients": [
      { "id": 4, "name": "Canned Tuna", "quantity": 1, "unit": "pcs" },
      { "id": 5, "name": "Mayonnaise", "quantity": 50, "unit": "g" },
      { "id": 6, "name": "Bread", "quantity": 2, "unit": "pcs" }
    ]
  },

  {
    "id": 3,
    "title": "Grilled Chicken Breast",
    "description": "Juicy grilled chicken breast with herbs.",
    "image_url": "https://www.recipetineats.com/tachyon/2024/02/Lemon-garlic-salmon-tray-bake_1.jpg",
    "category": "with_light",
    "type_of_dish": "dinner",
    "cooking_time": 30,
    "complexity": "medium",
    "view_count": 201,
    "instructions": [
      { "id": 1, "recipe_title": "Grilled Chicken Breast", "text": "1. Season chicken with herbs and salt." },
      { "id": 2, "recipe_title": "Grilled Chicken Breast", "text": "2. Grill on medium heat for 6-7 minutes per side until fully cooked." }
    ],
    "ingredients": [
      { "id": 7, "name": "Chicken Breast", "quantity": 2, "unit": "pcs" },
      { "id": 8, "name": "Olive Oil", "quantity": 20, "unit": "ml" },
      { "id": 9, "name": "Mixed Herbs", "quantity": 5, "unit": "g" }
    ]
  },

  {
    "id": 4,
    "title": "Fresh Greek Salad",
    "description": "Refreshing salad with tomatoes, cucumbers, olives, and feta.",
    "image_url": "https://s.lightorangebean.com/media/20240914152454/Fresh-Veggie-Hummus-Wrap_-done.png",
    "category": "no_light",
    "type_of_dish": "lunch",
    "cooking_time": 15,
    "complexity": "easy",
    "view_count": 176,
    "instructions": [
      { "id": 1, "recipe_title": "Fresh Greek Salad", "text": "1. Chop vegetables." },
      { "id": 2, "recipe_title": "Fresh Greek Salad", "text": "2. Mix with olives and feta." },
      { "id": 3, "recipe_title": "Fresh Greek Salad", "text": "3. Drizzle with olive oil and sprinkle with oregano." }
    ],
    "ingredients": [
      { "id": 10, "name": "Tomatoes", "quantity": 3, "unit": "pcs" },
      { "id": 11, "name": "Cucumber", "quantity": 1, "unit": "pcs" },
      { "id": 12, "name": "Feta Cheese", "quantity": 150, "unit": "g" }
    ]
  },
  {
    "id": 5,
    "title": "Pasta Carbonara",
    "description": "Classic Italian pasta with creamy egg sauce and bacon.",
    "image_url": "https://marleyspoon.com/media/recipes/343934/main_photos/large/creamy_carbonara_with_spaghetti-728518fc7780c4fca376270ae0817ab4.jpeg",
    "category": "with_light",
    "type_of_dish": "dinner",
    "cooking_time": 25,
    "complexity": "medium",
    "view_count": 305,
    "instructions": [
      { "id": 1, "recipe_title": "Pasta Carbonara", "text": "1. Cook pasta." },
      { "id": 2, "recipe_title": "Pasta Carbonara", "text": "2. Fry bacon." },
      { "id": 3, "recipe_title": "Pasta Carbonara", "text": "3. Mix eggs with cheese." },
      { "id": 4, "recipe_title": "Pasta Carbonara", "text": "4. Combine everything off heat to create creamy sauce." }
    ],
    "ingredients": [
      { "id": 13, "name": "Pasta", "quantity": 250, "unit": "g" },
      { "id": 14, "name": "Eggs", "quantity": 2, "unit": "pcs" },
      { "id": 15, "name": "Bacon", "quantity": 150, "unit": "g" }
    ]
  },
  {
    "id": 6,
    "title": "Overnight Oats",
    "description": "Healthy oats soaked overnight with milk and fruits.",
    "image_url": "https://www.cookingclassy.com/wp-content/uploads/2018/04/Overnight-Oats-12.jpg",
    "category": "no_light",
    "type_of_dish": "breakfast",
    "cooking_time": 5,
    "complexity": "easy",
    "view_count": 150,
    "instructions": [
      { "id": 1, "recipe_title": "Overnight Oats", "text": "1. Mix oats with milk and honey." },
      { "id": 2, "recipe_title": "Overnight Oats", "text": "2. Leave overnight in fridge." },
      { "id": 3, "recipe_title": "Overnight Oats", "text": "3. Add fruits before serving." }
    ],
    "ingredients": [
      { "id": 16, "name": "Oats", "quantity": 80, "unit": "g" },
      { "id": 17, "name": "Milk", "quantity": 200, "unit": "ml" },
      { "id": 18, "name": "Honey", "quantity": 15, "unit": "g" }
    ]
  },
  {
    "id": 7,
    "title": "Vegetable Stir Fry",
    "description": "Quick stir-fried vegetables with soy sauce.",
    "image_url": "https://ichef.bbci.co.uk/food/ic/food_16x9_1600/recipes/beef_pepper_stir_fry_88499_16x9.jpg",
    "category": "with_light",
    "type_of_dish": "dinner",
    "cooking_time": 20,
    "complexity": "easy",
    "view_count": 189,
    "instructions": [
      { "id": 1, "recipe_title": "Vegetable Stir Fry", "text": "1. Heat oil in pan." },
      { "id": 2, "recipe_title": "Vegetable Stir Fry", "text": "2. Add chopped vegetables." },
      { "id": 3, "recipe_title": "Vegetable Stir Fry", "text": "3. Stir fry for 7-10 minutes." },
      { "id": 4, "recipe_title": "Vegetable Stir Fry", "text": "4. Add soy sauce and serve." }
    ],
    "ingredients": [
      { "id": 19, "name": "Bell Pepper", "quantity": 1, "unit": "pcs" },
      { "id": 20, "name": "Broccoli", "quantity": 200, "unit": "g" },
      { "id": 21, "name": "Soy Sauce", "quantity": 30, "unit": "ml" }
    ]
  },
  {
    "id": 8,
    "title": "Peanut Butter Banana Wrap",
    "description": "Simple wrap with peanut butter and banana slices.",
    "image_url": "https://s.lightorangebean.com/media/20240914152454/Fresh-Veggie-Hummus-Wrap_-done.png",
    "category": "no_light",
    "type_of_dish": "breakfast",
    "cooking_time": 5,
    "complexity": "easy",
    "view_count": 87,
    "instructions": [
      { "id": 1, "recipe_title": "Peanut Butter Banana Wrap", "text": "1. Spread peanut butter on tortilla." },
      { "id": 2, "recipe_title": "Peanut Butter Banana Wrap", "text": "2. Add banana slices." },
      { "id": 3, "recipe_title": "Peanut Butter Banana Wrap", "text": "3. Roll tightly and slice." }
    ],
    "ingredients": [
      { "id": 22, "name": "Tortilla", "quantity": 1, "unit": "pcs" },
      { "id": 23, "name": "Peanut Butter", "quantity": 40, "unit": "g" },
      { "id": 24, "name": "Banana", "quantity": 1, "unit": "pcs" }
    ]
  },

  {
    "id": 9,
    "title": "Baked Salmon",
    "description": "Oven-baked salmon with lemon and herbs.",
    "image_url": "https://www.recipetineats.com/tachyon/2024/02/Lemon-garlic-salmon-tray-bake_1.jpg",
    "category": "with_light",
    "type_of_dish": "dinner",
    "cooking_time": 25,
    "complexity": "medium",
    "view_count": 260,
    "instructions": [
      { "id": 1, "recipe_title": "Baked Salmon", "text": "1. Season salmon with salt, pepper, lemon juice." },
      { "id": 2, "recipe_title": "Baked Salmon", "text": "2. Bake at 180°C for 20 minutes." }
    ],
    "ingredients": [
      { "id": 25, "name": "Salmon Fillet", "quantity": 2, "unit": "pcs" },
      { "id": 26, "name": "Lemon", "quantity": 1, "unit": "pcs" },
      { "id": 27, "name": "Olive Oil", "quantity": 15, "unit": "ml" }
    ]
  },

  {
    "id": 10,
    "title": "Caprese Salad",
    "description": "Tomato, mozzarella, and basil salad.",
    "image_url": "https://s.lightorangebean.com/media/20240914152454/Fresh-Veggie-Hummus-Wrap_-done.png",
    "category": "no_light",
    "type_of_dish": "lunch",
    "cooking_time": 10,
    "complexity": "easy",
    "view_count": 142,
    "instructions": [
      { "id": 1, "recipe_title": "Caprese Salad", "text": "1. Slice tomatoes and mozzarella." },
      { "id": 2, "recipe_title": "Caprese Salad", "text": "2. Layer with basil leaves." },
      { "id": 3, "recipe_title": "Caprese Salad", "text": "3. Drizzle olive oil and season." }
    ],
    "ingredients": [
      { "id": 28, "name": "Tomatoes", "quantity": 2, "unit": "pcs" },
      { "id": 29, "name": "Mozzarella", "quantity": 200, "unit": "g" },
      { "id": 30, "name": "Basil", "quantity": 5, "unit": "g" }
    ]
  },

  {
    "id": 11,
    "title": "Scrambled Eggs",
    "description": "Soft scrambled eggs with butter.",
    "image_url": "https://eggs.ca/wp-content/uploads/2024/06/Scrambled-Eggs-with-Cheese-1664x834-1.jpg",
    "category": "with_light",
    "type_of_dish": "breakfast",
    "cooking_time": 10,
    "complexity": "easy",
    "view_count": 210,
    "instructions": [
      { "id": 1, "recipe_title": "Scrambled Eggs", "text": "1. Whisk eggs." },
      { "id": 2, "recipe_title": "Scrambled Eggs", "text": "2. Cook slowly in butter while stirring until creamy." }
    ],
    "ingredients": [
      { "id": 31, "name": "Eggs", "quantity": 3, "unit": "pcs" },
      { "id": 32, "name": "Butter", "quantity": 20, "unit": "g" }
    ]
  },
  {
    "id": 12,
    "title": "Cold Pasta Salad",
    "description": "Pre-cooked pasta mixed with vegetables and dressing.",
    "image_url": "https://marleyspoon.com/media/recipes/343934/main_photos/large/creamy_carbonara_with_spaghetti-728518fc7780c4fca376270ae0817ab4.jpeg",
    "category": "no_light",
    "type_of_dish": "lunch",
    "cooking_time": 15,
    "complexity": "easy",
    "view_count": 119,
    "instructions": [
      { "id": 1, "recipe_title": "Cold Pasta Salad", "text": "1. Mix pre-cooked pasta with chopped vegetables and dressing." },
      { "id": 2, "recipe_title": "Cold Pasta Salad", "text": "2. Chill before serving." }
    ],
    "ingredients": [
      { "id": 33, "name": "Cooked Pasta", "quantity": 300, "unit": "g" },
      { "id": 34, "name": "Cherry Tomatoes", "quantity": 150, "unit": "g" },
      { "id": 35, "name": "Olive Oil", "quantity": 20, "unit": "ml" }
    ]
  },
  {
    "id": 13,
    "title": "Beef Stew",
    "description": "Slow-cooked beef with vegetables.",
    "image_url": "https://ichef.bbci.co.uk/food/ic/food_16x9_1600/recipes/beef_pepper_stir_fry_88499_16x9.jpg",
    "category": "with_light",
    "type_of_dish": "dinner",
    "cooking_time": 60,
    "complexity": "hard",
    "view_count": 180,
    "instructions": [
      { "id": 1, "recipe_title": "Beef Stew", "text": "1. Brown beef." },
      { "id": 2, "recipe_title": "Beef Stew", "text": "2. Add vegetables and broth." },
      { "id": 3, "recipe_title": "Beef Stew", "text": "3. Simmer for 1 hour until tender." }
    ],
    "ingredients": [
      { "id": 36, "name": "Beef", "quantity": 500, "unit": "g" },
      { "id": 37, "name": "Carrot", "quantity": 2, "unit": "pcs" },
      { "id": 38, "name": "Potatoes", "quantity": 3, "unit": "pcs" }
    ]
  },
  {
    "id": 14,
    "title": "Energy Snack Plate",
    "description": "Plate with nuts, cheese, fruits, and crackers.",
    "image_url": "https://cdn11.bigcommerce.com/s-cjh14ahqln/product_images/uploaded_images/tunacannellinibeansalad-1-web.jpg",
    "category": "no_light",
    "type_of_dish": "lunch",
    "cooking_time": 5,
    "complexity": "easy",
    "view_count": 75,
    "instructions": [
      { "id": 1, "recipe_title": "Energy Snack Plate", "text": "1. Arrange nuts, sliced cheese, fruits, and crackers on a plate." },
      { "id": 2, "recipe_title": "Energy Snack Plate", "text": "2. Serve immediately." }
    ],
    "ingredients": [
      { "id": 39, "name": "Mixed Nuts", "quantity": 100, "unit": "g" },
      { "id": 40, "name": "Cheese", "quantity": 150, "unit": "g" },
      { "id": 41, "name": "Crackers", "quantity": 10, "unit": "pcs" }
    ]
  },
  {
    "id": 15,
    "title": "Omelette with Vegetables",
    "description": "Fluffy omelette filled with fresh vegetables.",
    "image_url": "https://eggs.ca/wp-content/uploads/2024/06/Scrambled-Eggs-with-Cheese-1664x834-1.jpg",
    "category": "with_light",
    "type_of_dish": "breakfast",
    "cooking_time": 15,
    "complexity": "easy",
    "view_count": 165,
    "instructions": [
      { "id": 1, "recipe_title": "Omelette with Vegetables", "text": "1. Whisk eggs." },
      { "id": 2, "recipe_title": "Omelette with Vegetables", "text": "2. Pour into pan." },
      { "id": 3, "recipe_title": "Omelette with Vegetables", "text": "3. Add chopped vegetables." },
      { "id": 4, "recipe_title": "Omelette with Vegetables", "text": "4. Fold and cook until set." }
    ],
    "ingredients": [
      { "id": 42, "name": "Eggs", "quantity": 3, "unit": "pcs" },
      { "id": 43, "name": "Bell Pepper", "quantity": 1, "unit": "pcs" },
      { "id": 44, "name": "Spinach", "quantity": 50, "unit": "g" }
    ]
  },
  {
    "id": 16,
    "title": "Couscous Salad",
    "description": "Light couscous salad with fresh herbs.",
    "image_url": "https://cdn77-s3.lazycatkitchen.com/wp-content/uploads/2019/11/vegan-mushroom-risotto-close-1000x1500.jpg",
    "category": "with_light",
    "type_of_dish": "lunch",
    "cooking_time": 20,
    "complexity": "medium",
    "view_count": 132,
    "instructions": [
      { "id": 1, "recipe_title": "Couscous Salad", "text": "1. Prepare couscous with hot water." },
      { "id": 2, "recipe_title": "Couscous Salad", "text": "2. Mix with chopped vegetables and herbs." }
    ],
    "ingredients": [
      { "id": 45, "name": "Couscous", "quantity": 200, "unit": "g" },
      { "id": 46, "name": "Cucumber", "quantity": 1, "unit": "pcs" },
      { "id": 47, "name": "Parsley", "quantity": 10, "unit": "g" }
    ]
  },
  {
    "id": 17,
    "title": "Chicken Wrap",
    "description": "Grilled chicken wrapped in tortilla with vegetables.",
    "image_url": "https://s.lightorangebean.com/media/20240914152454/Fresh-Veggie-Hummus-Wrap_-done.png",
    "category": "with_light",
    "type_of_dish": "lunch",
    "cooking_time": 20,
    "complexity": "easy",
    "view_count": 144,
    "instructions": [
      { "id": 1, "recipe_title": "Chicken Wrap", "text": "1. Cook chicken pieces." },
      { "id": 2, "recipe_title": "Chicken Wrap", "text": "2. Place in tortilla with vegetables and sauce." },
      { "id": 3, "recipe_title": "Chicken Wrap", "text": "3. Roll and serve." }
    ],
    "ingredients": [
      { "id": 48, "name": "Chicken Breast", "quantity": 1, "unit": "pcs" },
      { "id": 49, "name": "Tortilla", "quantity": 1, "unit": "pcs" },
      { "id": 50, "name": "Lettuce", "quantity": 50, "unit": "g" }
    ]
  },
  {
    "id": 18,
    "title": "Fruit Yogurt Bowl",
    "description": "Creamy yogurt topped with fresh fruits and honey.",
    "image_url": "https://www.cookingclassy.com/wp-content/uploads/2018/04/Overnight-Oats-12.jpg",
    "category": "no_light",
    "type_of_dish": "breakfast",
    "cooking_time": 5,
    "complexity": "easy",
    "view_count": 158,
    "instructions": [
      { "id": 1, "recipe_title": "Fruit Yogurt Bowl", "text": "1. Pour yogurt into bowl." },
      { "id": 2, "recipe_title": "Fruit Yogurt Bowl", "text": "2. Add sliced fruits and drizzle honey on top." }
    ],
    "ingredients": [
      { "id": 51, "name": "Yogurt", "quantity": 200, "unit": "g" },
      { "id": 52, "name": "Strawberries", "quantity": 100, "unit": "g" },
      { "id": 53, "name": "Honey", "quantity": 10, "unit": "g" }
    ]
  },
  {
    "id": 19,
    "title": "Pan-Fried Shrimp",
    "description": "Garlic shrimp cooked in butter.",
    "image_url": "https://www.recipetineats.com/tachyon/2024/02/Lemon-garlic-salmon-tray-bake_1.jpg",
    "category": "with_light",
    "type_of_dish": "dinner",
    "cooking_time": 15,
    "complexity": "medium",
    "view_count": 223,
    "instructions": [
      { "id": 1, "recipe_title": "Pan-Fried Shrimp", "text": "1. Heat butter in pan." },
      { "id": 2, "recipe_title": "Pan-Fried Shrimp", "text": "2. Add garlic and shrimp." },
      { "id": 3, "recipe_title": "Pan-Fried Shrimp", "text": "3. Cook 2-3 minutes per side." }
    ],
    "ingredients": [
      { "id": 54, "name": "Shrimp", "quantity": 300, "unit": "g" },
      { "id": 55, "name": "Garlic", "quantity": 3, "unit": "pcs" },
      { "id": 56, "name": "Butter", "quantity": 30, "unit": "g" }
    ]
  },
  {
    "id": 20,
    "title": "No-Cook Hummus Plate",
    "description": "Hummus served with fresh vegetables and pita bread.",
    "image_url": "https://s.lightorangebean.com/media/20240914152454/Fresh-Veggie-Hummus-Wrap_-done.png",
    "category": "no_light",
    "type_of_dish": "dinner",
    "cooking_time": 5,
    "complexity": "easy",
    "view_count": 110,
    "instructions": [
      { "id": 1, "recipe_title": "No-Cook Hummus Plate", "text": "1. Place hummus in bowl." },
      { "id": 2, "recipe_title": "No-Cook Hummus Plate", "text": "2. Arrange sliced vegetables and pita around it." },
      { "id": 3, "recipe_title": "No-Cook Hummus Plate", "text": "3. Serve immediately." }
    ],
    "ingredients": [
      { "id": 57, "name": "Hummus", "quantity": 200, "unit": "g" },
      { "id": 58, "name": "Pita Bread", "quantity": 2, "unit": "pcs" },
      { "id": 59, "name": "Carrot Sticks", "quantity": 150, "unit": "g" }
    ]
  }
 
]
